xchainpy_util/__init__.py
xchainpy_util/asset.py
xchainpy_util/chain.py
xchainpy_util-0.1.8.dist-info/LICENSE
xchainpy_util-0.1.8.dist-info/METADATA
xchainpy_util-0.1.8.dist-info/WHEEL
xchainpy_util-0.1.8.dist-info/top_level.txt
xchainpy_util-0.1.8.dist-info/RECORD
